{
    "aka": null,
    "articleTotalCount": 0,
    "articles": [],
    "articlesAvailable": false,
    "category": "Indica",
    "conditions": [
        {
            "name": "ADD/ADHD",
            "score": 1.4705882352941175
        },
        {
            "name": "Anorexia",
            "score": 1.4705882352941175
        },
        {
            "name": "Anxiety",
            "score": 1.4705882352941175
        },
        {
            "name": "Arthritis",
            "score": 1.4705882352941175
        },
        {
            "name": "Asthma",
            "score": 1.4705882352941175
        }
    ],
    "description": "<p>Grape Drink is a sweet cross of familiar genetics. <a href=\"https://www.leafly.com/hybrid/kimbo-kush\">Kimbo Kush</a> x <a href=\"https://www.leafly.com/hybrid/grape-god\">Grape God</a> offer their best attributes to this indica, expressing themselves as large spear-shaped colas from Kimbo Kush and the intoxicatingly sweet aroma of Grape God. While Grape Drink&rsquo;s sweet candy flavor is enough to win over consumers from coast to coast, its luscious body effects and reflective mental state make it a must-have. Enjoy Grape Drink in small doses for a manageable all-day indica, but continue to consume this heady cut and anticipate heavy body effects that lead toward rest and relaxation. &nbsp; &nbsp; &nbsp;&nbsp;</p>\n",
    "descriptionPlain": "Grape Drink is a sweet cross of familiar genetics. Kimbo Kush x Grape God offer their best attributes to this indica, expressing themselves as large spear-shaped colas from Kimbo Kush and the intoxicatingly sweet aroma of Grape God. While Grape Drink&rsquo;s sweet candy flavor is enough to win over consumers from coast to coast, its luscious body effects and reflective mental state make it a must-have. Enjoy Grape Drink in small doses for a manageable all-day indica, but continue to consume this heady cut and anticipate heavy body effects that lead toward rest and relaxation. &nbsp; &nbsp; &nbsp;&nbsp;\n",
    "effects": [
        {
            "name": "Tingly",
            "score": 2.941176470588235
        },
        {
            "name": "Creative",
            "score": 2.941176470588235
        },
        {
            "name": "Euphoric",
            "score": 2.941176470588235
        },
        {
            "name": "Giggly",
            "score": 2.941176470588235
        },
        {
            "name": "Happy",
            "score": 2.941176470588235
        }
    ],
    "flavors": [
        {
            "name": "Grape",
            "score": 4.411764705882353
        },
        {
            "name": "Sweet",
            "score": 2.941176470588235
        },
        {
            "name": "Flowery",
            "score": 2.941176470588235
        },
        {
            "name": "Spicy/Herbal",
            "score": 1.4705882352941175
        },
        {
            "name": "Berry",
            "score": 1.4705882352941175
        }
    ],
    "growInfo": {
        "averageYield": null,
        "difficulty": null,
        "environment": null,
        "floweringDays": 0,
        "growNotes": "",
        "height": null,
        "outdoorFinish": null,
        "preferredMedium": null
    },
    "highlightedReviews": [
        {
            "avatar": "https://ddd33q3967xhi.cloudfront.net/EsB9lXCri57tN17h49dVOnCDkFI=/fit-in/300x300/https%3a%2f%2fs3.amazonaws.com%2fleafly%2fbin%2fTBeeQQk0TGeLYj4SjC6Z_old-school-red.png",
            "id": 1330947,
            "starImage": "https://d3ix816x6wuc0d.cloudfront.net/stars/5/240",
            "text": "Very good high, I love it!",
            "username": "DJGarcia906"
        },
        {
            "avatar": "https://ddd33q3967xhi.cloudfront.net/LN9qqi4LLaHMKnh02esy-mIM7HY=/fit-in/300x300/https%3a%2f%2fs3.amazonaws.com%2fleafly%2fbin%2f81c50UjRtmwRXtUVVQKw_aviator-purple.png",
            "id": 1355336,
            "starImage": "https://d3ix816x6wuc0d.cloudfront.net/stars/5/240",
            "text": "I got this strain from The Highway in Colorado. It was grown outdoor in the Keystone mountains at altitude. It is the darkest purple I have seen and the biggest outdoor purple nugs I have seen in awhile. Definitely the hardest hitting indica I have had. Great strain!",
            "username": "liftedtiki5"
        }
    ],
    "id": 253776,
    "name": "Grape Drink",
    "negatives": [],
    "parents": [
        {
            "applink": "leafly://strain/kimbo-kush",
            "category": "Hybrid",
            "name": "Kimbo Kush",
            "permalink": "https://mobileapi.leafly.com/hybrid/kimbo-kush",
            "slug": "kimbo-kush",
            "subtitle": null,
            "symbol": "Kim"
        },
        {
            "applink": "leafly://strain/grape-god",
            "category": "Hybrid",
            "name": "Grape God",
            "permalink": "https://mobileapi.leafly.com/hybrid/grape-god",
            "slug": "grape-god",
            "subtitle": null,
            "symbol": "Gg"
        }
    ],
    "permalink": "https://mobileapi.leafly.com/indica/grape-drink",
    "photoTotalCount": 1,
    "photos": [
        {
            "fullsize": "https://d3ix816x6wuc0d.cloudfront.net/cdn/strain-photo/586122/b/grape-drink__primary_86dd.jpg",
            "thumb": "https://leafly-s3.s3.amazonaws.com/leafly/reviews/grape-drink_100x100_f897.jpg",
            "uploaded": "/Date(-62135596800000)/"
        }
    ],
    "popularCities": [
        "Denver, CO",
        "Ritzville, WA"
    ],
    "rating": 4.67,
    "relatedStrains": [],
    "reviewCount": 6,
    "sl_translate": "description,descriptionPlain,category",
    "slug": "grape-drink",
    "starImage": "https://d3ix816x6wuc0d.cloudfront.net/stars/4.66666666666667/240",
    "subtitle": null,
    "symbol": "Gdn",
    "symptoms": [
        {
            "name": "Depression",
            "score": 2.941176470588235
        },
        {
            "name": "Pain",
            "score": 2.941176470588235
        },
        {
            "name": "Stress",
            "score": 2.941176470588235
        },
        {
            "name": "Eye Pressure",
            "score": 1.4705882352941175
        },
        {
            "name": "Fatigue",
            "score": 1.4705882352941175
        }
    ],
    "testGraph": null,
    "videoUrl": null,
    "weakDescription": false
}
